flask_toolkit/__init__.py
flask_toolkit/application.py
flask_toolkit/infra/__init__.py
flask_toolkit/infra/event_bus/__init__.py
flask_toolkit/infra/logging/__init__.py
flask_toolkit/infra/security/__init__.py
flask_toolkit/infra/security/cryptor.py
flask_toolkit/infra/validator/__init__.py
flask_toolkit/settings/__init__.py
flask_toolkit/shared/__init__.py
flask_toolkit/shared/choice_mixin.py
flask_toolkit/shared/domain_event.py
flask_toolkit/shared/domain_service.py
flask_toolkit/shared/entity.py
flask_toolkit/shared/exceptions.py
flask_toolkit/shared/payload_wrap.py
flask_toolkit/shared/repository.py
flask_toolkit/shared/representer.py
flask_toolkit/shared/singleton.py
flask_toolkit/shared/strong_parameters.py
flask_toolkit/shared/use_case.py
flask_toolkit-0.0.5.dist-info/METADATA
flask_toolkit-0.0.5.dist-info/RECORD
flask_toolkit-0.0.5.dist-info/WHEEL
flask_toolkit-0.0.5.dist-info/top_level.txt
tests/__init__.py
tests/conftest.py
tests/test_app_error_handlers.py
tests/test_health_check.py
tests/infra/__init__.py
tests/infra/security/__init__.py
tests/infra/security/test_cryptor.py
tests/shared/__init__.py
tests/shared/test_domain_event.py
tests/shared/test_domain_service.py
tests/shared/test_entity.py
tests/shared/test_exceptions.py
tests/shared/test_representer.py
