Metadata-Version: 2.1
Name: flask-toolkit
Version: 0.0.5
Summary: Flask toolkit for Domain Driven Design (DDD)
Home-page: https://github.com/creditas/flask-toolkit
Author: Aurelio Saraiva
Author-email: aurelio.saraiva@creditas.com.br
License: UNKNOWN
Platform: UNKNOWN
Classifier: Programming Language :: Python :: 3
Classifier: License :: OSI Approved :: MIT License
Classifier: Operating System :: OS Independent
Requires-Dist: marshmallow (==2.15.0)
Requires-Dist: Flask-Log-Request-ID (==0.10.0)
Requires-Dist: Logentries (==0.17)
Requires-Dist: Flask-Migrate (==2.1.1)
Requires-Dist: Flask-Cors (==3.0.3)
Requires-Dist: Flask (==0.12.2)
Requires-Dist: blinker (==1.4)
Requires-Dist: event-bus (==1.0.2)
Requires-Dist: aead (==0.2)
